{
  "@context": "https://schema.org",
  "@type": "BlogPosting",
  "@id": "https://www.alanranger.com/blog-on-photography/best-product-photography-tripod#blogposting",
  "headline": "The Best Product Photography Tripod: Review and Features",
  "alternativeHeadline": "The Best Product Photography Tripod: Review and Features | Alan Ranger Photography",
  "description": "Table of Contents Show Introduction - K&F (Kent Faith) 94\"/2.4m Overhead Camera Tripod paired with the K&F Concept 3-Way Geared Tripod Head Capturing.",
  "url": "https://www.alanranger.com/blog-on-photography/best-product-photography-tripod",
  "datePublished": "2024-11-13T00:00:00.000Z",
  "dateModified": "2024-11-13T00:00:00.000Z",
  "dateCreated": "2024-11-13T00:00:00.000Z",
  "inLanguage": "en-GB",
  "articleBody": "The Best Product Photography Tripod: Review and Features Table of Contents Show Introduction - K&F (Kent Faith) 94\"/2.4m Overhead Camera Tripod paired with the K&F Concept 3-Way Geared Tripod Head Capturing high-quality product images requires precision, stability, and the right equipment. A tripod with a horizontal centre column and a geared head is invaluable for overhead product photography. This review of The Best Product Photography Tripod evaluates the K&F 94\"/2.4m Overhead Camera Tripod paired with the K&F Concept 3-Way Geared Tripod Head, showcasing its features, performance, and how it compares to other models in the market. Why a Dedicated Product Photography Tripod Matters Product photography demands exacting standards. Achieving sharp, distortion-free images involves: • Stability: Prevents camera shake for crisp shots. Precision: Ensures the camera is perfectly aligned with the product. The 94\"/2.4m Overhead Camera Tripod and the K&F Concept 3-Way Geared Tripod Head deliver on both fronts, making them an excellent choice for professional and aspiring product photographers. Key Features of the 94\"/2.4m Overhead Camera Tripod This tripod’s standout feature is its horizontal centre column, perfect for overhead shooting. Its highlights include: Horizontal Centre Column Boom: Allows positioning the camera directly above the subject for flat lays and macro shots. Robust Construction: Made of aluminium, the tripod supports up to 10kg (22lbs), accommodating professional DSLR and mirrorless setups. Height and Flexibility: Extends to 2.4m (94”), offering excellent reach, while adjustable legs provide stability on uneven surfaces. Detachable Monopod: Adds versatility, useful for photographers who also shoot on location. This tripod is a versatile and durable tool for both studio and on-location work. Benefits of the K&F Concept 3-Way Geared Tripod Head The K&F Concept 3-Way Geared Tripod Head brings precision to the setup. Its features include: Three-Axis Control: Provides precise adjustments on pan, tilt, and roll axes for perfect alignment. Smooth Operation: Fluid head movement ensures precise positioning without disruption. Durable Build: CNC-machined aluminium alloy construction supports up to 6kg (13.2lbs), suitable for most cameras and lenses. This geared head is ideal for photographers who need meticulous control in their compositions. Real-World TestingReal-World Testing: Performance and Practical Use Straight out of the box, I ensured all the tripod joints were properly tightened. This is a common practice, as tripods often arrive with detachable components slightly loosened to make users aware they can be swapped or adjusted. The 94\"/2.4m Overhead Camera Tripod comes with a standard ball head, which performs adequately in general use. However, for this test, I specifically opted to pair it with the K&F Concept 3-Way Geared Head, and swapping the heads was a quick and straightforward process. Testing the Horizontal Arm Mechanism One of my primary objectives was to test the functionality of the horizontal centre column. I was pleasantly surprised at how intuitive this feature was to use. The centre column consists of two sections, with the horizontal arm lifting seamlessly from within the main column. It then pivots effortlessly into the horizontal position. To maintain balance, I removed the hook from the bottom of the main centre column and reattached it to the head of the horizontal arm. This allowed me to add counterweight, which is essential when using heavier camera equipment. Stability with Heavy Gear For the test, I mounted my Sony mirrorless camera paired with a 70-200mm lens, resulting in a combined weight of 1.6kg. Without a counterweight on the opposite end of the horizontal arm, the setup would have been prone to toppling. By properly counterbalancing the arm, I was able to extend it fully to the stop mark without any stability issues. Performance of the 3-Way Geared Tripod Head With my camera securely mounted and positioned for overhead shots, the K&F Concept 3-Way Geared Tripod Head excelled in providing precise adjustments. Small tweaks to the composition were smooth and secure, with no fear of the camera slipping or instability. Even with the camera positioned directly over the product at a 180-degree angle, the setup felt solid and dependable. Overall Impressions Setting up the tripod was quick and hassle-free, and transitioning to the horizontal arm position was straightforward. The combination of the tripod and the 3-way geared head made photographing products from top-down angles and various other perspectives a seamless experience. The stability, ease of use, and precision adjustments provided a professional-grade solution for overhead product photography. How This Setup Excels in Product Photography Overhead Shooting Made Easy In studio testing, the setup performed exceptionally for flat lay photography. The horizontal column made it easy to frame items precisely, while the geared head enabled fine adjustments. Even with heavier equipment, the tripod remained stable, producing sharp images with no need for additional post-production alignment. The horizontal centre column allows for true overhead shots while maintaining stability. The locking mechanism keeps the column secure, even with heavy cameras. The geared head ensures the lens aligns perfectly perpendicular to the product, avoiding distortion. Ease of Use and Portability Despite its professional-grade features, the tripod is straightforward to use: Setup and Adjustment: The horizontal column transitions smoothly, and the geared head allows precise adjustments without hassle. Portability: While heavier than travel tripods, the detachable monopod and foldable design make it suitable for location shoots. Its weight may be a limitation for those prioritising ultra-portable setups, but its functionality outweighs this drawback for studio use. How It Compares to Other Product Photography Tripods To understand its value, let’s compare this setup with other popular options on the market. PriceMid-range (£250-£300)High-end (£400-£450)Mid-range (£150-£200)Premium (£600-£800)Build MaterialAluminiumAluminiumAluminiumAluminiumMax Height2.4m (94”)1.7m (67”)1.93m (76”)1.6m (63”)Weight Capacity10kg (22lbs)8kg (17.6lbs)10kg (22lbs)8kg (17.6lbs)Geared Head FunctionalityYes, 3-axisYes, 3-axisNo, ball headNo, ball headHorizontal Centre ColumnYesYesYesYesPortabilityModerate (detachable monopod)ModerateModerateModerateBest ForStudio and overhead product photographyProfessional studio workOverhead and macro photographyCreative compositions Why the 94” Overhead Camera Tripod Stands Out The K&F 94” tripod offers an excellent balance of functionality, price, and versatility. Its horizontal centre column and geared head make it superior for overhead product photography compared to budget options like Neewer’s tripod, while its price and performance rival high-end models like the Manfrotto 055. For photographers who value precision without a premium price tag, it is a clear winner. Where to buy? I am pleased to pass on an exclusive discount to my clients for this product photography set-up when you purchase directly from the manufacturer. Discount code: Alan22 It is an exclusive 22% Off sitewide code End time:2025/6/30 94\"/2.4m Overhead Camera Tripod aluminium Tripod Transverse Center Column with Detachable Monopod for DSLR K&F Concept 3-Way Geared Tripod Head CNC Process Aluminum Alloy, High-Precision Fluid Head FAQs About Product Photography Tripods 1. Can this tripod handle heavy professional cameras?Yes, the tripod supports up to 10kg (22lbs), while the geared head accommodates up to 6kg (13.2lbs). 2. Is it suitable for outdoor use?While primarily designed for studio use, the tripod’s aluminium build and detachable monopod make it versatile for outdoor shoots. 3. Does the horizontal centre column affect stability?No, the locking mechanism ensures the column remains stable even when fully extended. 4. What are the maintenance requirements?Regular cleaning of joints and ensuring all locks are tightened will keep the tripod and head functioning smoothly. 5. What makes a geared head better for product photography?Geared heads allow for precise adjustments on three axes, ensuring perfect alignment for overhead and close-up shots. Final Thoughts: Is This the Best Product Photography Tripod? For studio-based photographers, the 94\"/2.4m Overhead Camera Tripod paired with the K&F Concept 3-Way Geared Tripod Head delivers exceptional performance. Its robust build, precise adjustments, and versatility make it an outstanding tool for overhead product photography. While not the most portable option, its value for studio and controlled setups is hard to beat. This tripod is a must-have for those seeking a professional-grade yet affordable solution for their product photography needs. recommended-productsAlan Ranger13 November 2024Alan Ranger Photographyessential gear guides LinkedIn0 Pinterest0",
  "wordCount": 1291,
  "image": {
    "@id": "https://www.alanranger.com/blog-on-photography/best-product-photography-tripod#primaryimage"
  },
  "author": {
    "@id": "https://www.alanranger.com/#person"
  },
  "publisher": {
    "@id": "https://www.alanranger.com/#org"
  },
  "isPartOf": {
    "@id": "https://www.alanranger.com/#website"
  },
  "mainEntityOfPage": {
    "@id": "https://www.alanranger.com/blog-on-photography/best-product-photography-tripod#webpage"
  },
  "about": [
    {
      "@type": "Thing",
      "name": "Photographic composition"
    }
  ]
}