{
  "@context": "https://schema.org",
  "@type": "BlogPosting",
  "@id": "https://www.alanranger.com/blog-on-photography/photography-basics-creative-editing#blogposting",
  "headline": "Tip of the day - photography basics - Creative Editing",
  "alternativeHeadline": "Tip of the day - photography basics - Creative Editing | Alan Ranger Photography",
  "description": "Tip of the day - photography basics - Creative Editing.",
  "url": "https://www.alanranger.com/blog-on-photography/photography-basics-creative-editing",
  "datePublished": "2021-06-01T23:00:00.000Z",
  "dateModified": "2021-06-01T23:00:00.000Z",
  "dateCreated": "2021-06-01T23:00:00.000Z",
  "inLanguage": "en-GB",
  "articleBody": "",
  "wordCount": 0,
  "image": {
    "@id": "https://www.alanranger.com/blog-on-photography/photography-basics-creative-editing#primaryimage"
  },
  "author": {
    "@id": "https://www.alanranger.com/#person"
  },
  "publisher": {
    "@id": "https://www.alanranger.com/#org"
  },
  "isPartOf": {
    "@id": "https://www.alanranger.com/#website"
  },
  "mainEntityOfPage": {
    "@id": "https://www.alanranger.com/blog-on-photography/photography-basics-creative-editing#webpage"
  }
}