{
  "@context": "https://schema.org",
  "@type": "WebPage",
  "@id": "https://www.alanranger.com/blog-on-photography/product-photography-ideas#webpage",
  "url": "https://www.alanranger.com/blog-on-photography/product-photography-ideas",
  "name": "Product Photography Ideas",
  "description": "Product Photography Ideas.",
  "inLanguage": "en-GB",
  "isPartOf": {
    "@id": "https://www.alanranger.com/#website"
  },
  "about": {
    "@id": "https://www.alanranger.com/blog-on-photography/product-photography-ideas#blogposting"
  },
  "mainEntity": {
    "@id": "https://www.alanranger.com/blog-on-photography/product-photography-ideas#blogposting"
  }
}