{
  "@context": "https://schema.org",
  "@type": "WebPage",
  "@id": "https://www.alanranger.com/blog-on-photography/product-photography-ideas#webpage",
  "url": "https://www.alanranger.com/blog-on-photography/product-photography-ideas",
  "name": "30 Fresh Product Photography Ideas to Elevate Your Brand",
  "description": "This guide you’ll get 30 product photography ideas you can try today, plus tips on when to DIY and when to hire a pro.r.",
  "inLanguage": "en-GB",
  "isPartOf": {
    "@id": "https://www.alanranger.com/#website"
  },
  "about": {
    "@id": "https://www.alanranger.com/blog-on-photography/product-photography-ideas#blogposting"
  },
  "mainEntity": {
    "@id": "https://www.alanranger.com/blog-on-photography/product-photography-ideas#blogposting"
  }
}