{
  "@context": "https://schema.org",
  "@type": "WebPage",
  "@id": "https://www.alanranger.com/blog-on-photography/used-cameras-and-lenses#webpage",
  "url": "https://www.alanranger.com/blog-on-photography/used-cameras-and-lenses",
  "name": "Used Camera Equipment cameras and Lenses - From UK retailers",
  "description": "A tool for photographers to find used camera equipment from over 60 UK retailers. Searches for used camera gear from MPB, Wex, Park Cameras, and many more.",
  "inLanguage": "en-GB",
  "isPartOf": {
    "@id": "https://www.alanranger.com/#website"
  },
  "about": {
    "@id": "https://www.alanranger.com/blog-on-photography/used-cameras-and-lenses#blogposting"
  },
  "mainEntity": {
    "@id": "https://www.alanranger.com/blog-on-photography/used-cameras-and-lenses#blogposting"
  }
}