{
  "@context": "https://schema.org",
  "@type": "WebPage",
  "@id": "https://www.alanranger.com/blog-on-photography/using-a-nd-filter#webpage",
  "url": "https://www.alanranger.com/blog-on-photography/using-a-nd-filter",
  "name": "Using a ND Filter for Long Exposure Photography | A Guide",
  "description": "What a ND (Neutral Density) filter does and how to use them I have been using neutral density filters for many years now and have enjoyed the affects you.",
  "inLanguage": "en-GB",
  "isPartOf": {
    "@id": "https://www.alanranger.com/#website"
  },
  "about": {
    "@id": "https://www.alanranger.com/blog-on-photography/using-a-nd-filter#blogposting"
  },
  "mainEntity": {
    "@id": "https://www.alanranger.com/blog-on-photography/using-a-nd-filter#blogposting"
  }
}